{
  "project_info": {
    "project_number": "172958636194",
    "firebase_url": "https://gesturetalk-f1045.firebaseio.com",
    "project_id": "gesturetalk-f1045",
    "storage_bucket": "gesturetalk-f1045.appspot.com"
  },
  "client": [
    {
      "client_info": {
        "mobilesdk_app_id": "1:172958636194:android:774cc10f57390f67675ffb",
        "android_client_info": {
          "package_name": "com.stockman.mlkitgesturetalk"
        }
      },
      "oauth_client": [
        {
          "client_id": "172958636194-s89kjkd3phnggrc94dqp3nf497n1hrms.apps.googleusercontent.com",
          "client_type": 3
        }
      ],
      "api_key": [
        {
          "current_key": "AIzaSyAvraCUBCn6n2wCZbN1qCvcD3S-HUljweI"
        }
      ],
      "services": {
        "appinvite_service": {
          "other_platform_oauth_client": [
            {
              "client_id": "172958636194-s89kjkd3phnggrc94dqp3nf497n1hrms.apps.googleusercontent.com",
              "client_type": 3
            }
          ]
        }
      }
    }
  ],
  "configuration_version": "1"
}